pymvn/__init__.py
pymvn/__main__.py
pymvn/__main__tpl.py
pymvn/init.py
pymvn/integrate.py
pymvn/parsepybuild.py
pymvn-0.0.1.dist-info/METADATA
pymvn-0.0.1.dist-info/WHEEL
pymvn-0.0.1.dist-info/top_level.txt
pymvn-0.0.1.dist-info/RECORD
