Metadata-Version: 2.1
Name: pymvn
Version: 0.0.1
Summary: package python src and site-packages into *.zip,
Home-page: https://github.com/Mng12345/pymvn
Author: zhangming
Author-email: 1570977353@qq.com
Maintainer: zhangming
Maintainer-email: 1570977353@qq.com
License: BSD License
Platform: all
Classifier: Development Status :: 4 - Beta
Classifier: Operating System :: OS Independent
Classifier: Intended Audience :: Developers
Classifier: License :: OSI Approved :: BSD License
Classifier: Programming Language :: Python
Classifier: Programming Language :: Python :: Implementation
Classifier: Programming Language :: Python :: 3.7
Classifier: Topic :: Software Development :: Libraries
